{
  "method": "petsc_gamg_fresh",
  "setup_time_s": 0.0009229183197021484,
  "solve_time_s": 0.09365266468029776,
  "total_time_s": 0.09457558299999991,
  "linear_solver_calls": 2,
  "velocity_krylov_iterations": 144,
  "velocity_solve_calls": 18,
  "max_linear_relative_residual": 7.836276711877315e-09,
  "max_solution_relative_error_vs_direct": 5.9114226561523194e-09,
  "python_peak_memory_bytes": 192038,
  "velocity_fallbacks": 0,
  "pressure_fallbacks": 0,
  "full_fallbacks": 0,
  "hierarchy_setups": 2,
  "hierarchy_updates": 0,
  "hierarchy_rebuilds": 2,
  "hierarchy_reuses": 0,
  "hierarchy_decisions": [
    {
      "step": 0,
      "reason": "initial_setup",
      "matrix_change": Infinity
    },
    {
      "step": 1,
      "reason": "initial_setup",
      "matrix_change": 0.6231482998070418
    }
  ],
  "backend_setup_failures": 0,
  "preconditioner_apply_calls": 182,
  "preconditioner_apply_time_s": 0.0028067109999980744,
  "backend_errors": [],
  "method_rss_baseline_bytes": 177586176,
  "method_peak_rss_bytes": 178421760,
  "method_peak_rss_delta_bytes": 835584,
  "quality_accepted": true,
  "status": "success",
  "n": 2,
  "seed": 0,
  "viscosity_contrast": 100.0,
  "trajectory_generation_time_s": 0.15995633399999998,
  "nodal_viscosity_min": 3.098610280688699,
  "nodal_viscosity_max": 100.0,
  "nodal_viscosity_contrast": 32.27253218103115,
  "element_viscosity_min": 3.415389991671617,
  "element_viscosity_max": 100.0,
  "element_viscosity_contrast": 29.279233189723183,
  "trajectory_sparse_bytes": 44832,
  "mesh_mode": "unstructured",
  "dimension": 3,
  "n_nodes": 16,
  "n_elements": 53,
  "velocity_dofs": 48,
  "stokes_dofs": 64,
  "thermo_stokes_dofs": 80,
  "unstructured_points": 8,
  "viscosity_mode": "temperature_strain_rate",
  "peak_rss_bytes": 180256768,
  "repeat": 0,
  "subprocess_wall_time_s": 1.3267140409999953
}